buildgrid_metering/__init__.py
buildgrid_metering/py.typed
buildgrid_metering/client/__init__.py
buildgrid_metering/client/auth.py
buildgrid_metering/client/client.py
buildgrid_metering/client/exceptions.py
buildgrid_metering/client/retry.py
buildgrid_metering/models/__init__.py
buildgrid_metering/models/api.py
buildgrid_metering/models/dataclasses.py
buildgrid_metering_client-0.0.4.dist-info/LICENSE
buildgrid_metering_client-0.0.4.dist-info/METADATA
buildgrid_metering_client-0.0.4.dist-info/WHEEL
buildgrid_metering_client-0.0.4.dist-info/top_level.txt
buildgrid_metering_client-0.0.4.dist-info/RECORD
