Metadata-Version: 2.1
Name: buildgrid-metering-client
Version: 0.0.4
Summary: Client library of buildgrid-metering service
License: 
Project-URL: homepage, https://gitlab.com/BuildGrid/buildgrid-metering-client
Project-URL: repository, https://gitlab.com/BuildGrid/buildgrid-metering-client.git
Keywords: buildgrid
Classifier: Development Status :: 3 - Alpha
Classifier: Programming Language :: Python :: 3
Classifier: License :: OSI Approved :: Apache Software License
Requires-Python: >=3.8
License-File: LICENSE
Requires-Dist: pydantic >=1.10
Requires-Dist: aiohttp >=3.8
Requires-Dist: async-lru >=2.0
Requires-Dist: tenacity >=8.2
Requires-Dist: cachetools >=5.3
Requires-Dist: requests >=2.31.0
Provides-Extra: dev
Requires-Dist: pytest ; extra == 'dev'
Requires-Dist: pytest-cov ; extra == 'dev'
Requires-Dist: pytest-asyncio ; extra == 'dev'
Requires-Dist: httpx ; extra == 'dev'
Requires-Dist: mypy ; extra == 'dev'
Requires-Dist: types-cachetools ; extra == 'dev'
Requires-Dist: types-requests >=2.31.0 ; extra == 'dev'
Requires-Dist: isort ; extra == 'dev'
Requires-Dist: black ; extra == 'dev'
Requires-Dist: flake8 ; extra == 'dev'
